[
  {
    "type": "replace",
    "path": "/stemcells/alias=xenial/version",
    "value": "170.129"
  },
  {
    "type": "replace",
    "path": "/releases/name=concourse",
    "value": {
      "name": "concourse",
      "version": "5.5.1",
      "url": "https://storage.googleapis.com/control-tower-compiled-releases/concourse-5.5.1-ubuntu-xenial-170.129-20190913-191526-848815702.tgz",
      "stemcell": {
        "os": "ubuntu-xenial",
        "version": "170.129"
      }
    }
  },
  {
    "type": "replace",
    "path": "/releases/name=bpm",
    "value": {
      "name": "bpm",
      "version": "1.0.4",
      "url": "https://storage.googleapis.com/control-tower-compiled-releases/bpm-1.0.4-ubuntu-xenial-170.129-20190913-191803-519067131.tgz",
      "stemcell": {
        "os": "ubuntu-xenial",
        "version": "170.129"
      }
    }
  },
  {
    "type": "replace",
    "path": "/releases/name=grafana",
    "value": {
      "name": "grafana",
      "version": "13.3.0",
      "url": "https://storage.googleapis.com/control-tower-compiled-releases/grafana-13.3.0-ubuntu-xenial-170.129-20190913-191825-443159331.tgz",
      "stemcell": {
        "os": "ubuntu-xenial",
        "version": "170.129"
      }
    }
  },
  {
    "type": "replace",
    "path": "/releases/name=influxdb",
    "value": {
      "name": "influxdb",
      "version": "8.0.4",
      "url": "https://storage.googleapis.com/control-tower-compiled-releases/influxdb-8.0.4-ubuntu-xenial-170.129-20190913-191852-628918492.tgz",
      "stemcell": {
        "os": "ubuntu-xenial",
        "version": "170.129"
      }
    }
  },
  {
    "type": "replace",
    "path": "/releases/name=credhub",
    "value": {
      "name": "credhub",
      "version": "2.5.6",
      "url": "https://storage.googleapis.com/control-tower-compiled-releases/credhub-2.5.6-ubuntu-xenial-170.129-20190913-191924-83793726.tgz",
      "stemcell": {
        "os": "ubuntu-xenial",
        "version": "170.129"
      }
    }
  },
  {
    "type": "replace",
    "path": "/releases/name=uaa",
    "value": {
      "name": "uaa",
      "version": "70.0",
      "url": "https://storage.googleapis.com/control-tower-compiled-releases/uaa-70.0-ubuntu-xenial-170.129-20190913-192027-276471732.tgz",
      "stemcell": {
        "os": "ubuntu-xenial",
        "version": "170.129"
      }
    }
  },
  {
    "type": "replace",
    "path": "/releases/name=bosh-dns",
    "value": {
      "name": "bosh-dns",
      "version": "1.10.0",
      "url": "https://storage.googleapis.com/control-tower-compiled-releases/bosh-dns-1.10.0-ubuntu-xenial-170.129-20190913-192117-081278817.tgz",
      "stemcell": {
        "os": "ubuntu-xenial",
        "version": "170.129"
      }
    }
  },
  {
    "type": "replace",
    "path": "/releases/name=telegraf",
    "value": {
      "name": "telegraf",
      "version": "4",
      "url": "https://storage.googleapis.com/control-tower-compiled-releases/telegraf-4-ubuntu-xenial-170.129-20190913-192136-207059425.tgz",
      "stemcell": {
        "os": "ubuntu-xenial",
        "version": "170.129"
      }
    }
  },
  {
    "type": "replace",
    "path": "/releases/name=telegraf-agent",
    "value": {
      "name": "telegraf-agent",
      "version": "1",
      "url": "https://storage.googleapis.com/control-tower-compiled-releases/telegraf-agent-1-ubuntu-xenial-170.129-20190913-192142-014643977.tgz",
      "stemcell": {
        "os": "ubuntu-xenial",
        "version": "170.129"
      }
    }
  }
]